{"player": {"1": {"id": 1, "nom": "among", "prenom": "remi", "dob": "20/01/1995", "points": 0}, "2": {"id": 2, "nom": "azerting", "prenom": "alexander", "dob": "25/03/1999", "points": 2}, "3": {"id": 3, "nom": "butalo", "prenom": "maxime", "dob": "29/02/2001", "points": 1}, "4": {"id": 4, "nom": "fang", "prenom": "zing", "dob": "30/08/1978", "points": 1}, "5": {"id": 5, "nom": "otuper", "prenom": "carlos", "dob": "01/07/1960", "points": 0}, "6": {"id": 6, "nom": "zenba", "prenom": "lucas", "dob": "18/11/1958", "points": 0}, "7": {"id": 7, "nom": "karamine", "prenom": "Kamel", "dob": "20/01/1980", "points": 0}, "8": {"id": 8, "nom": "lambri", "prenom": "tarik", "dob": "14/02/1984", "points": 0}, "9": {"id": 9, "nom": "sqd", "prenom": "sqd", "dob": "20/01/2002", "points": 0}}, "tournament": {"1": {"id": 1, "nom": "mini echecs", "location": "Paris", "start": "13-10-2023-17-36", "end": "13-10-2023-17-37", "round_total": 2, "rounds": [1, 2], "players": [1, 2, 3, 4], "description": "tournois pour les petits"}, "2": {"id": 2, "nom": "Tournois Pr\u00e9sentation", "location": "Paris", "start": "26-10-2023-16-59", "end": "not finish", "round_total": 4, "rounds": [3], "players": [1, 2, 3, 4, 5, 6, 7, 8], "description": "Tournois pour voir qui est le meilleur "}}, "round": {"1": {"roundId": 1, "tournoisId": 1, "name": "Round 1", "start": "13-10-2023-17-36", "end": "13-10-2023-17-36", "finish": true}, "2": {"roundId": 2, "tournoisId": 1, "name": "Round 2", "start": "13-10-2023-17-37", "end": "13-10-2023-17-37", "finish": true}, "3": {"roundId": 3, "tournoisId": 2, "name": "Round 1", "start": "26-10-2023-16-59", "end": "after", "finish": false}}, "match": {"1": {"matchId": 1, "roundId": 1, "player1": 2, "player2": 3, "scores": [1, 0], "finish": true}, "2": {"matchId": 2, "roundId": 1, "player1": 4, "player2": 1, "scores": [1, 0], "finish": true}, "3": {"matchId": 3, "roundId": 2, "player1": 2, "player2": 4, "scores": [2, 1], "finish": true}, "4": {"matchId": 4, "roundId": 2, "player1": 3, "player2": 1, "scores": [1, 0], "finish": true}, "5": {"matchId": 5, "roundId": 3, "player1": 1, "player2": 7, "scores": [0, 0], "finish": false}, "6": {"matchId": 6, "roundId": 3, "player1": 3, "player2": 8, "scores": [0, 0], "finish": false}, "7": {"matchId": 7, "roundId": 3, "player1": 6, "player2": 4, "scores": [0, 0], "finish": false}, "8": {"matchId": 8, "roundId": 3, "player1": 2, "player2": 5, "scores": [0, 0], "finish": false}}}